tkpdf/__init__.py
tkpdf/pdfview.py
tkpdf-0.1.3.dist-info/LICENSE
tkpdf-0.1.3.dist-info/METADATA
tkpdf-0.1.3.dist-info/WHEEL
tkpdf-0.1.3.dist-info/top_level.txt
tkpdf-0.1.3.dist-info/RECORD
