Metadata-Version: 2.1
Name: tkpdf
Version: 0.1.3
Summary: PDF viewer for Tkinter.
Home-page: https://github.com/rdbende/tkpdf
Author: rdbende
Author-email: rdbende@gmail.com
License: MIT license
Platform: UNKNOWN
Classifier: Programming Language :: Python :: 3.6
Classifier: License :: OSI Approved :: MIT License
Classifier: Operating System :: OS Independent
Requires-Python: >=3.6
Requires-Dist: pymupdf
